shoopack/__init__.py
shoopack/base.py
shoopack/factory.py
shoopack/utils.py
shoopack/validator.py
shoopack/impl/__init__.py
shoopack/impl/azmq/__init__.py
shoopack/impl/azmq/pubsub.py
shoopack/impl/azmq/reqres.py
shoopack/impl/zmq/__init__.py
shoopack/impl/zmq/pubsub.py
shoopack/impl/zmq/reqres.py
shoopack/ipc/__init__.py
shoopack/ipc/kafka.py
shoopack/ipc/redis.py
shoopack/ipc/zmq.py
shoopack-0.0.0a1.dist-info/ipc/__init__.py
shoopack-0.0.0a1.dist-info/ipc/kafka.py
shoopack-0.0.0a1.dist-info/ipc/redis.py
shoopack-0.0.0a1.dist-info/ipc/zmq.py
shoopack-0.0.0a1.dist-info/METADATA
shoopack-0.0.0a1.dist-info/WHEEL
shoopack-0.0.0a1.dist-info/__init__.py
shoopack-0.0.0a1.dist-info/top_level.txt
shoopack-0.0.0a1.dist-info/RECORD
