Metadata-Version: 2.4
Name: shoopack
Version: 0.0.0a1
Summary: A short description of your package
Home-page: https://github.com/4am-ciss/shoopack
Author: zygn
Author-email: zygn <rikochet@kakao.com>
License: MIT
Requires-Python: >=3.8
Requires-Dist: pyzmq
Dynamic: author
Dynamic: home-page
Dynamic: requires-python
